wnote/__init__.py
wnote/cli.py
wnote/commands/__init__.py
wnote/commands/attachment_commands.py
wnote/commands/backup_commands.py
wnote/commands/config_commands.py
wnote/commands/export_commands.py
wnote/commands/note_commands.py
wnote/commands/reminder_commands.py
wnote/commands/tag_commands.py
wnote/core/__init__.py
wnote/core/config.py
wnote/core/database.py
wnote/utils/__init__.py
wnote/utils/decorators.py
wnote/utils/file_ops.py
wnote/utils/formatters.py
wnote-0.6.1.dist-info/licenses/LICENSE
wnote-0.6.1.dist-info/METADATA
wnote-0.6.1.dist-info/WHEEL
wnote-0.6.1.dist-info/entry_points.txt
wnote-0.6.1.dist-info/top_level.txt
wnote-0.6.1.dist-info/RECORD
