Metadata-Version: 2.4
Name: wnote
Version: 0.6.1
Summary: Terminal Note Taking Application with beautiful UI and rich features
Home-page: https://github.com/imnotnahn/wnote
Author: imnahn
Author-email: 
Maintainer: imnahn
License: MIT
Project-URL: Homepage, https://github.com/imnotnahn/wnote
Project-URL: Documentation, https://github.com/imnotnahn/wnote#readme
Project-URL: Repository, https://github.com/imnotnahn/wnote
Project-URL: Bug Tracker, https://github.com/imnotnahn/wnote/issues
Keywords: notes,note-taking,cli,terminal,productivity,organization
Classifier: Development Status :: 4 - Beta
Classifier: Environment :: Console
Classifier: Intended Audience :: Developers
Classifier: Intended Audience :: End Users/Desktop
Classifier: License :: OSI Approved :: MIT License
Classifier: Operating System :: OS Independent
Classifier: Programming Language :: Python :: 3
Classifier: Programming Language :: Python :: 3.7
Classifier: Programming Language :: Python :: 3.8
Classifier: Programming Language :: Python :: 3.9
Classifier: Programming Language :: Python :: 3.10
Classifier: Programming Language :: Python :: 3.11
Classifier: Programming Language :: Python :: 3.12
Classifier: Topic :: Office/Business
Classifier: Topic :: Utilities
Classifier: Topic :: Text Processing
Requires-Python: >=3.7
License-File: LICENSE
Requires-Dist: click>=8.1.7
Requires-Dist: rich>=13.7.0
Requires-Dist: requests>=2.28.0
Requires-Dist: colorama>=0.4.6
Requires-Dist: tabulate>=0.9.0
Requires-Dist: markdown>=3.4.0
Provides-Extra: dev
Requires-Dist: pytest>=7.0.0; extra == "dev"
Requires-Dist: pytest-cov>=4.0.0; extra == "dev"
Requires-Dist: black>=23.0.0; extra == "dev"
Requires-Dist: isort>=5.12.0; extra == "dev"
Requires-Dist: mypy>=1.0.0; extra == "dev"
Requires-Dist: flake8>=6.0.0; extra == "dev"
Dynamic: home-page
Dynamic: license-file
Dynamic: requires-python
